nvidia_sphinx_theme/__init__.py
nvidia_sphinx_theme/assets/scripts/index.js
nvidia_sphinx_theme/assets/styles/base/_base.scss
nvidia_sphinx_theme/assets/styles/components/_prev-next.scss
nvidia_sphinx_theme/assets/styles/components/_readthedocs-switcher.scss
nvidia_sphinx_theme/assets/styles/components/_search.scss
nvidia_sphinx_theme/assets/styles/components/_sidebar.scss
nvidia_sphinx_theme/assets/styles/components/header/_header-logo.scss
nvidia_sphinx_theme/assets/styles/content/_api.scss
nvidia_sphinx_theme/assets/styles/content/_figures.scss
nvidia_sphinx_theme/assets/styles/content/_lists.scss
nvidia_sphinx_theme/assets/styles/index.scss
nvidia_sphinx_theme/assets/styles/sections/_footer.scss
nvidia_sphinx_theme/assets/styles/sections/_header.scss
nvidia_sphinx_theme/assets/styles/sections/_sidebar-primary.scss
nvidia_sphinx_theme/assets/styles/variables/_color.scss
nvidia_sphinx_theme/assets/styles/variables/_fonts.scss
nvidia_sphinx_theme/assets/styles/variables/_layout.scss
nvidia_sphinx_theme/theme/nvidia_sphinx_theme/components/copyright.html
nvidia_sphinx_theme/theme/nvidia_sphinx_theme/components/extra-footer.html
nvidia_sphinx_theme/theme/nvidia_sphinx_theme/components/feedback.html
nvidia_sphinx_theme/theme/nvidia_sphinx_theme/components/footer-links.html
nvidia_sphinx_theme/theme/nvidia_sphinx_theme/components/footer-logo.html
nvidia_sphinx_theme/theme/nvidia_sphinx_theme/components/navbar-external-links.html
nvidia_sphinx_theme/theme/nvidia_sphinx_theme/components/sidebar-nav-bs.html
nvidia_sphinx_theme/theme/nvidia_sphinx_theme/components/version-switcher.html
nvidia_sphinx_theme/theme/nvidia_sphinx_theme/layout.html
nvidia_sphinx_theme/theme/nvidia_sphinx_theme/search.html
nvidia_sphinx_theme/theme/nvidia_sphinx_theme/sections/sidebar-primary.html
nvidia_sphinx_theme/theme/nvidia_sphinx_theme/static/favicon.png
nvidia_sphinx_theme/theme/nvidia_sphinx_theme/static/nvidia-logo-horiz-rgb-1c-blk-for-screen.svg
nvidia_sphinx_theme-0.0.9.dist-info/LICENSE
nvidia_sphinx_theme-0.0.9.dist-info/METADATA
nvidia_sphinx_theme-0.0.9.dist-info/WHEEL
nvidia_sphinx_theme-0.0.9.dist-info/entry_points.txt
nvidia_sphinx_theme-0.0.9.dist-info/RECORD